helper_package/__init__.py
helper_package/helper_module.py
helper_package-0.1.0.dist-info/METADATA
helper_package-0.1.0.dist-info/WHEEL
helper_package-0.1.0.dist-info/top_level.txt
helper_package-0.1.0.dist-info/RECORD
